voidchat/__init__.py
voidchat/__main__.py
voidchat/agent.py
voidchat/cli.py
voidchat/config.py
voidchat/context_slimmer.py
voidchat/context_tree.py
voidchat/init.py
voidchat/local_tools.py
voidchat/mcp_client.py
voidchat/memory.py
voidchat/skills.py
voidchat/thread_index.py
voidchat/workspace_state.py
voidchat-0.1.0.dist-info/METADATA
voidchat-0.1.0.dist-info/WHEEL
voidchat-0.1.0.dist-info/entry_points.txt
voidchat-0.1.0.dist-info/top_level.txt
voidchat-0.1.0.dist-info/RECORD
