Metadata-Version: 2.4
Name: voidchat
Version: 0.1.0
Summary: MCP + Skills enabled CLI/REPL chat agent
Requires-Python: >=3.10
Requires-Dist: mcp==1.25.0
Requires-Dist: openai==2.14.0
Requires-Dist: python-dotenv==1.2.1
Requires-Dist: pyyaml==6.0.3
Requires-Dist: prompt-toolkit==3.0.52
Provides-Extra: pptx-tools
Requires-Dist: python-pptx; extra == "pptx-tools"
Requires-Dist: pillow; extra == "pptx-tools"
Requires-Dist: six; extra == "pptx-tools"
Requires-Dist: defusedxml; extra == "pptx-tools"
Requires-Dist: lxml; extra == "pptx-tools"
